merida/__about__.py
merida/__init__.py
merida/lightcurves_cls.py
merida/matching_stars.py
merida/metadata_cls.py
merida/moa9yr_lightcurve_cls.py
merida/moa_rereduced_lightcurve_cls.py
merida/ra_dec_converter.py
merida/season_determiner.py
merida/server_for_lightcurves.py
merida/sumi_tags.py
merida/zones_for_lightcurves.py
merida/analysis/valid_data_points.py
merida-0.3.2.dist-info/METADATA
merida-0.3.2.dist-info/WHEEL
merida-0.3.2.dist-info/licenses/LICENSE
merida-0.3.2.dist-info/RECORD
