Metadata-Version: 2.4
Name: merida
Version: 0.3.2
Summary: MERIDA: MOA9yr Exploration and Research Interface for Dataset Analysis Resources
Project-URL: Homepage, https://github.com/stelais/merida
Author: Stela IS, Greg O, MERIDA authors
Author-email: Stela IS <stela.ishitanisilva@nasa.gov>
License-Expression: MIT
License-File: LICENSE
Requires-Python: >=3.9
Requires-Dist: astropy>=6.0.0
Requires-Dist: beautifulsoup4>=4.13.3
Requires-Dist: bokeh>=3.4.1
Requires-Dist: html5lib>=1.1
Requires-Dist: lxml>=4.9.3
Requires-Dist: numpy>=1.26.2
Requires-Dist: pandas>=2.1.4
Requires-Dist: pyarrow>=14.0.1
Requires-Dist: pytest-pycharm>=0.7.0
Requires-Dist: pytest>=7.1.3
Requires-Dist: requests>=2.32.0
Requires-Dist: tqdm>=4.66.3
